{
    "ID1": [
        [
            "BA.2.75"
        ]
    ],
    "ID2": [
        [
            "BQ.1.1"
        ]
    ],
    "ID3": [
        [
            "BA.5.2.13"
        ]
    ],
    "ID4": [
        [
            "BF.7"
        ]
    ],
    "ID5": [
        [
            "BQ.1.8"
        ]
    ],
    "ID6": [
        [
            "BQ.1.1"
        ]
    ],
    "ID7": [
        [
            "BA.2.75"
        ]
    ],
    "ID8": [
        [
            "other"
        ]
    ],
    "ID9": [
        [
            "BA.5.2"
        ]
    ],
    "ID10": [
        [
            "BF.7"
        ]
    ],
    "ID11": [
        [
            "BQ.1"
        ]
    ],
    "ID12": [
        [
            "BQ.1.1"
        ]
    ],
    "ID13": [
        [
            "BQ.1"
        ]
    ],
    "ID14": [
        [
            "BQ.1"
        ]
    ],
    "ID15": [
        [
            "other"
        ]
    ],
    "ID16": [
        [
            "BQ.1"
        ]
    ],
    "ID17": [
        [
            "BQ.1.1.8"
        ]
    ],
    "ID18": [
        [
            "BA.5.2"
        ]
    ],
    "ID19": [
        [
            "BQ.1"
        ]
    ],
    "ID20": [
        [
            "BN.1"
        ]
    ],
    "ID21": [
        [
            "BA.5.2.1"
        ]
    ],
    "ID22": [
        [
            "BQ.1.1"
        ]
    ],
    "ID23": [
        [
            "BN.1"
        ]
    ],
    "ID24": [
        [
            "BA.5.2"
        ]
    ],
    "ID25": [
        [
            "BA.5.2.13"
        ]
    ],
    "ID26": [
        [
            "BQ.1"
        ]
    ],
    "ID27": [
        [
            "BQ.1"
        ]
    ],
    "ID28": [
        [
            "BQ.1"
        ]
    ],
    "ID29": [
        [
            "BQ.1"
        ]
    ],
    "ID30": [
        [
            "BA.5.2.1"
        ]
    ],
    "ID31": [
        [
            "BA.2.75"
        ]
    ],
    "ID32": [
        [
            "BA.5.2.1"
        ]
    ],
    "ID33": [
        [
            "BQ.1.1"
        ]
    ],
    "ID34": [
        [
            "BQ.1.1"
        ]
    ],
    "ID35": [
        [
            "BA.5.2.1"
        ]
    ],
    "ID36": [
        [
            "BQ.1"
        ]
    ],
    "ID37": [
        [
            "BQ.1.1"
        ]
    ],
    "ID38": [
        [
            "BQ.1.1"
        ]
    ],
    "ID39": [
        [
            "BQ.1.1"
        ]
    ],
    "ID40": [
        [
            "BQ.1.1"
        ]
    ],
    "ID41": [
        [
            "BA.5.2"
        ]
    ],
    "ID42": [
        [
            "BQ.1.1"
        ]
    ],
    "ID43": [
        [
            "BA.5.2"
        ]
    ],
    "ID44": [
        [
            "BA.5",
            883,
            "BA.5.2"
        ]
    ],
    "ID45": [
        [
            "BA.2.75"
        ]
    ],
    "ID46": [
        [
            "BN.1"
        ]
    ],
    "ID47": [
        [
            "BQ.1.1"
        ]
    ],
    "ID48": [
        [
            "BQ.1.1"
        ]
    ],
    "ID49": [
        [
            "BQ.1.1"
        ]
    ],
    "ID50": [
        [
            "BF.7"
        ]
    ],
    "ID51": [
        [
            "BQ.1.1.8"
        ]
    ],
    "ID52": [
        [
            "BA.2.75"
        ]
    ],
    "ID53": [
        [
            "BQ.1"
        ]
    ],
    "ID54": [
        [
            "other"
        ]
    ],
    "ID55": [
        [
            "BN.1"
        ]
    ],
    "ID56": [
        [
            "BQ.1.8"
        ]
    ],
    "ID57": [
        [
            "BQ.1.1.8"
        ]
    ],
    "ID58": [
        [
            "BA.2.75"
        ]
    ],
    "ID59": [
        [
            "BQ.1.1"
        ]
    ],
    "ID60": [
        [
            "BA.2.75",
            28575,
            "BA.5.1"
        ]
    ],
    "ID61": [
        [
            "BA.5.2.1",
            28334,
            "other"
        ]
    ],
    "ID62": [
        [
            "BF.11"
        ]
    ],
    "ID63": [
        [
            "BN.1"
        ]
    ],
    "ID64": [
        [
            "BQ.1"
        ]
    ],
    "ID65": [
        [
            "BQ.1.1"
        ]
    ],
    "ID66": [
        [
            "BN.1"
        ]
    ],
    "ID67": [
        [
            "BN.1"
        ]
    ],
    "ID68": [
        [
            "BQ.1.1"
        ]
    ],
    "ID69": [
        [
            "other"
        ]
    ],
    "ID70": [
        [
            "BA.5"
        ]
    ],
    "ID71": [
        [
            "BA.2.75"
        ]
    ],
    "ID72": [
        [
            "BQ.1"
        ]
    ],
    "ID73": [
        [
            "BA.5.2.13"
        ]
    ],
    "ID74": [
        [
            "BA.2.75"
        ]
    ],
    "ID75": [
        [
            "BA.5.2.35"
        ]
    ],
    "ID76": [
        [
            "BA.4.6"
        ]
    ],
    "ID77": [
        [
            "BA.5.2"
        ]
    ],
    "ID78": [
        [
            "BQ.1.8"
        ]
    ],
    "ID79": [
        [
            "BN.1"
        ]
    ],
    "ID80": [
        [
            "BA.5.2.35"
        ]
    ],
    "ID81": [
        [
            "other"
        ]
    ],
    "ID82": [
        [
            "BQ.1.1"
        ]
    ],
    "ID83": [
        [
            "BQ.1.8"
        ]
    ],
    "ID84": [
        [
            "BQ.1.1"
        ]
    ],
    "ID85": [
        [
            "BA.5.2"
        ]
    ],
    "ID86": [
        [
            "BQ.1.1"
        ]
    ],
    "ID87": [
        [
            "BA.5.2"
        ]
    ],
    "ID88": [
        [
            "BA.5.2",
            5426,
            "BA.5.2.1"
        ]
    ],
    "ID89": [
        [
            "BQ.1.1"
        ]
    ],
    "ID90": [
        [
            "BQ.1.1"
        ]
    ],
    "ID91": [
        [
            "BQ.1.1"
        ]
    ],
    "ID92": [
        [
            "BQ.1.1"
        ]
    ],
    "ID93": [
        [
            "BA.5.2.1"
        ]
    ],
    "ID94": [
        [
            "BQ.1.8"
        ]
    ],
    "ID95": [
        [
            "BQ.1"
        ]
    ],
    "ID96": [
        [
            "BQ.1.1"
        ]
    ],
    "ID97": [
        [
            "BQ.1"
        ]
    ],
    "ID98": [
        [
            "BQ.1.1"
        ]
    ],
    "ID99": [
        [
            "BQ.1.1"
        ]
    ],
    "ID100": [
        [
            "BA.4.6"
        ]
    ],
    "ID101": [
        [
            "BQ.1.1"
        ]
    ],
    "ID102": [
        [
            "BF.7"
        ]
    ],
    "ID103": [
        [
            "BA.5.2.35"
        ]
    ],
    "ID104": [
        [
            "BA.2.75"
        ]
    ],
    "ID105": [
        [
            "BQ.1.1"
        ]
    ],
    "ID106": [
        [
            "BF.11"
        ]
    ],
    "ID107": [
        [
            "BQ.1.1"
        ]
    ],
    "ID108": [
        [
            "other"
        ]
    ],
    "ID109": [
        [
            "BA.5.2.1"
        ]
    ],
    "ID110": [
        [
            "BQ.1.8"
        ]
    ],
    "ID111": [
        [
            "BQ.1.1"
        ]
    ],
    "ID112": [
        [
            "BQ.1"
        ]
    ],
    "ID113": [
        [
            "BA.5.2.13"
        ]
    ],
    "ID114": [
        [
            "BA.5.1"
        ]
    ],
    "ID115": [
        [
            "BQ.1.1"
        ]
    ],
    "ID116": [
        [
            "BA.5.1"
        ]
    ],
    "ID117": [
        [
            "BA.2.75"
        ]
    ],
    "ID118": [
        [
            "BA.5.2"
        ]
    ],
    "ID119": [
        [
            "BQ.1.1"
        ]
    ],
    "ID120": [
        [
            "BF.7"
        ]
    ],
    "ID121": [
        [
            "BQ.1.1"
        ]
    ],
    "ID122": [
        [
            "BA.5.2",
            626,
            "BA.5.2.35"
        ]
    ],
    "ID123": [
        [
            "BA.5.1"
        ]
    ],
    "ID124": [
        [
            "BA.5.2.1"
        ]
    ],
    "ID125": [
        [
            "BA.5.1"
        ]
    ],
    "ID126": [
        [
            "BQ.1.1"
        ]
    ],
    "ID127": [
        [
            "BA.5.1"
        ]
    ],
    "ID128": [
        [
            "BF.7"
        ]
    ],
    "ID129": [
        [
            "BA.2.75"
        ]
    ],
    "ID130": [
        [
            "BA.5.2.1"
        ]
    ],
    "ID131": [
        [
            "BQ.1.8"
        ]
    ],
    "ID132": [
        [
            "BQ.1.1"
        ]
    ],
    "ID133": [
        [
            "BQ.1.1"
        ]
    ],
    "ID134": [
        [
            "BQ.1.1"
        ]
    ],
    "ID135": [
        [
            "BQ.1.1"
        ]
    ],
    "ID136": [
        [
            "BQ.1"
        ]
    ],
    "ID137": [
        [
            "BQ.1.1"
        ]
    ],
    "ID138": [
        [
            "BF.11"
        ]
    ],
    "ID139": [
        [
            "BA.5"
        ]
    ],
    "ID140": [
        [
            "BA.5.2.1",
            23440,
            "BF.7"
        ],
        [
            "BF.7",
            27513,
            "BA.5.2.13"
        ]
    ],
    "ID141": [
        [
            "BA.5.2.1"
        ]
    ],
    "ID142": [
        [
            "BA.5.2.1"
        ]
    ],
    "ID143": [
        [
            "BQ.1.8"
        ]
    ],
    "ID144": [
        [
            "BQ.1.1"
        ]
    ],
    "ID145": [
        [
            "BN.1"
        ]
    ],
    "ID146": [
        [
            "BF.11"
        ]
    ],
    "ID147": [
        [
            "BQ.1.1"
        ]
    ],
    "ID148": [
        [
            "BQ.1"
        ]
    ],
    "ID149": [
        [
            "BA.2.75"
        ]
    ],
    "ID150": [
        [
            "BQ.1.8"
        ]
    ],
    "ID151": [
        [
            "BQ.1.1"
        ]
    ],
    "ID152": [
        [
            "BQ.1.1"
        ]
    ],
    "ID153": [
        [
            "BQ.1.8"
        ]
    ],
    "ID154": [
        [
            "BQ.1"
        ]
    ],
    "ID155": [
        [
            "BQ.1.8"
        ]
    ],
    "ID156": [
        [
            "BF.7"
        ]
    ],
    "ID157": [
        [
            "BQ.1.1"
        ]
    ],
    "ID158": [
        [
            "BA.2.75"
        ]
    ],
    "ID159": [
        [
            "BQ.1.1"
        ]
    ],
    "ID160": [
        [
            "BF.7"
        ]
    ],
    "ID161": [
        [
            "BQ.1.1"
        ]
    ],
    "ID162": [
        [
            "BF.7"
        ]
    ],
    "ID163": [
        [
            "BA.2.75"
        ]
    ],
    "ID164": [
        [
            "BA.5.2"
        ]
    ],
    "ID165": [
        [
            "BQ.1.1"
        ]
    ],
    "ID166": [
        [
            "BA.5.2"
        ]
    ],
    "ID167": [
        [
            "BQ.1.1"
        ]
    ],
    "ID168": [
        [
            "BQ.1"
        ]
    ],
    "ID169": [
        [
            "BN.1"
        ]
    ],
    "ID170": [
        [
            "BQ.1"
        ]
    ],
    "ID171": [
        [
            "BA.5.1"
        ]
    ],
    "ID172": [
        [
            "BN.1"
        ]
    ],
    "ID173": [
        [
            "BQ.1.1"
        ]
    ],
    "ID174": [
        [
            "BQ.1.1"
        ]
    ],
    "ID175": [
        [
            "BA.5.2"
        ]
    ],
    "ID176": [
        [
            "BF.7"
        ]
    ],
    "ID177": [
        [
            "BQ.1.1"
        ]
    ],
    "ID178": [
        [
            "BA.5.2"
        ]
    ],
    "ID179": [
        [
            "BF.7"
        ]
    ],
    "ID180": [
        [
            "BA.5.1"
        ]
    ],
    "ID181": [
        [
            "BA.5.2.1"
        ]
    ],
    "ID182": [
        [
            "BQ.1.1"
        ]
    ],
    "ID183": [
        [
            "BQ.1"
        ]
    ],
    "ID184": [
        [
            "BQ.1"
        ]
    ],
    "ID185": [
        [
            "BA.5.2.35"
        ]
    ],
    "ID186": [
        [
            "BQ.1.1"
        ]
    ],
    "ID187": [
        [
            "BQ.1.8"
        ]
    ],
    "ID188": [
        [
            "BQ.1.1"
        ]
    ],
    "ID189": [
        [
            "BQ.1.8"
        ]
    ],
    "ID190": [
        [
            "BA.5.2"
        ]
    ],
    "ID191": [
        [
            "BQ.1.1"
        ]
    ],
    "ID192": [
        [
            "BQ.1"
        ]
    ],
    "ID193": [
        [
            "BQ.1.1"
        ]
    ],
    "ID194": [
        [
            "BQ.1.1"
        ]
    ],
    "ID195": [
        [
            "BA.5.2"
        ]
    ],
    "ID196": [
        [
            "BA.5.1"
        ]
    ],
    "ID197": [
        [
            "BQ.1.1"
        ]
    ],
    "ID198": [
        [
            "BQ.1"
        ]
    ],
    "ID199": [
        [
            "BN.1"
        ]
    ],
    "ID200": [
        [
            "BQ.1.1"
        ]
    ],
    "ID201": [
        [
            "BQ.1.1"
        ]
    ],
    "ID202": [
        [
            "BQ.1"
        ]
    ],
    "ID203": [
        [
            "BA.5.2"
        ]
    ],
    "ID204": [
        [
            "BQ.1.8"
        ]
    ],
    "ID205": [
        [
            "BA.5"
        ]
    ],
    "ID206": [
        [
            "BQ.1.8"
        ]
    ],
    "ID207": [
        [
            "BQ.1"
        ]
    ],
    "ID208": [
        [
            "BQ.1.1"
        ]
    ],
    "ID209": [
        [
            "BF.7"
        ]
    ],
    "ID210": [
        [
            "BF.7"
        ]
    ],
    "ID211": [
        [
            "BA.2.75"
        ]
    ],
    "ID212": [
        [
            "BA.5.2"
        ]
    ],
    "ID213": [
        [
            "BQ.1.8"
        ]
    ],
    "ID214": [
        [
            "other"
        ]
    ],
    "ID215": [
        [
            "BA.5.1"
        ]
    ],
    "ID216": [
        [
            "BQ.1"
        ]
    ],
    "ID217": [
        [
            "BQ.1.1"
        ]
    ],
    "ID218": [
        [
            "BA.5",
            883,
            "BA.5.2"
        ]
    ],
    "ID219": [
        [
            "BQ.1"
        ]
    ],
    "ID220": [
        [
            "BQ.1.1"
        ]
    ],
    "ID221": [
        [
            "other"
        ]
    ],
    "ID222": [
        [
            "BA.5.2"
        ]
    ],
    "ID223": [
        [
            "BF.11"
        ]
    ],
    "ID224": [
        [
            "BQ.1.1"
        ]
    ],
    "ID225": [
        [
            "BQ.1.1"
        ]
    ],
    "ID226": [
        [
            "BA.5.2.1"
        ]
    ],
    "ID227": [
        [
            "BF.7"
        ]
    ],
    "ID228": [
        [
            "BA.2.75"
        ]
    ],
    "ID229": [
        [
            "BN.1"
        ]
    ],
    "ID230": [
        [
            "BQ.1.1"
        ]
    ],
    "ID231": [
        [
            "BA.5.1"
        ]
    ],
    "ID232": [
        [
            "BQ.1"
        ]
    ],
    "ID233": [
        [
            "BQ.1.1"
        ]
    ],
    "ID234": [
        [
            "BQ.1.1",
            29773,
            "other"
        ]
    ],
    "ID235": [
        [
            "BF.7"
        ]
    ],
    "ID236": [
        [
            "BQ.1.1"
        ]
    ],
    "ID237": [
        [
            "BN.1"
        ]
    ],
    "ID238": [
        [
            "BQ.1.1"
        ]
    ],
    "ID239": [
        [
            "BQ.1.1"
        ]
    ],
    "ID240": [
        [
            "BQ.1"
        ]
    ],
    "ID241": [
        [
            "BQ.1.8"
        ]
    ],
    "ID242": [
        [
            "BA.5.2"
        ]
    ],
    "ID243": [
        [
            "BA.2.75"
        ]
    ],
    "ID244": [
        [
            "BQ.1.1"
        ]
    ],
    "ID245": [
        [
            "BF.7"
        ]
    ],
    "ID246": [
        [
            "BQ.1.1"
        ]
    ],
    "ID247": [
        [
            "BQ.1.1"
        ]
    ],
    "ID248": [
        [
            "BA.5.2"
        ]
    ],
    "ID249": [
        [
            "BQ.1.8"
        ]
    ],
    "ID250": [
        [
            "BA.2.75"
        ]
    ],
    "ID251": [
        [
            "BQ.1.1.8"
        ]
    ],
    "ID252": [
        [
            "BQ.1.1"
        ]
    ],
    "ID253": [
        [
            "BQ.1.1"
        ]
    ],
    "ID254": [
        [
            "BQ.1.1.8"
        ]
    ],
    "ID255": [
        [
            "BQ.1"
        ]
    ],
    "ID256": [
        [
            "BQ.1.1"
        ]
    ],
    "ID257": [
        [
            "BQ.1.1"
        ]
    ],
    "ID258": [
        [
            "BQ.1.8"
        ]
    ],
    "ID259": [
        [
            "BQ.1"
        ]
    ],
    "ID260": [
        [
            "BF.7"
        ]
    ],
    "ID261": [
        [
            "BN.1"
        ]
    ],
    "ID262": [
        [
            "BQ.1.1",
            29773,
            "other"
        ]
    ],
    "ID263": [
        [
            "BQ.1.1"
        ]
    ],
    "ID264": [
        [
            "BQ.1.1"
        ]
    ],
    "ID265": [
        [
            "BA.5.2"
        ]
    ],
    "ID266": [
        [
            "BE.1"
        ]
    ],
    "ID267": [
        [
            "BQ.1.1"
        ]
    ],
    "ID268": [
        [
            "other"
        ]
    ],
    "ID269": [
        [
            "BQ.1"
        ]
    ],
    "ID270": [
        [
            "BQ.1.1"
        ]
    ],
    "ID271": [
        [
            "BF.7"
        ]
    ],
    "ID272": [
        [
            "BF.7"
        ]
    ],
    "ID273": [
        [
            "BQ.1.8"
        ]
    ],
    "ID274": [
        [
            "BQ.1.8"
        ]
    ],
    "ID275": [
        [
            "other"
        ]
    ],
    "ID276": [
        [
            "BA.4.6"
        ]
    ],
    "ID277": [
        [
            "BQ.1.1"
        ]
    ],
    "ID278": [
        [
            "BQ.1.1"
        ]
    ],
    "ID279": [
        [
            "BQ.1.1"
        ]
    ],
    "ID280": [
        [
            "BQ.1.1"
        ]
    ],
    "ID281": [
        [
            "BQ.1.8"
        ]
    ],
    "ID282": [
        [
            "BQ.1.8"
        ]
    ],
    "ID283": [
        [
            "BN.1"
        ]
    ],
    "ID284": [
        [
            "BQ.1.1"
        ]
    ],
    "ID285": [
        [
            "BA.5"
        ]
    ],
    "ID286": [
        [
            "BA.5.2"
        ]
    ],
    "ID287": [
        [
            "BQ.1.8"
        ]
    ],
    "ID288": [
        [
            "BF.7"
        ]
    ],
    "ID289": [
        [
            "BQ.1.1.8"
        ]
    ],
    "ID290": [
        [
            "BQ.1.1"
        ]
    ],
    "ID291": [
        [
            "BQ.1.1"
        ]
    ],
    "ID292": [
        [
            "BQ.1.1",
            11200,
            "BQ.1"
        ],
        [
            "BQ.1",
            21263,
            "BA.5.2"
        ],
        [
            "BA.5.2",
            22011,
            "BQ.1"
        ]
    ],
    "ID293": [
        [
            "other"
        ]
    ],
    "ID294": [
        [
            "BA.2.75"
        ]
    ],
    "ID295": [
        [
            "BA.4.6"
        ]
    ],
    "ID296": [
        [
            "BA.5.2"
        ]
    ],
    "ID297": [
        [
            "BF.11"
        ]
    ],
    "ID298": [
        [
            "BQ.1.1"
        ]
    ],
    "ID299": [
        [
            "BQ.1.1",
            17500,
            "BE.1"
        ],
        [
            "BE.1",
            22362,
            "BQ.1.8"
        ]
    ],
    "ID300": [
        [
            "BN.1"
        ]
    ],
    "ID301": [
        [
            "other"
        ]
    ],
    "ID302": [
        [
            "BA.5.2.13"
        ]
    ],
    "ID303": [
        [
            "BQ.1"
        ]
    ],
    "ID304": [
        [
            "BA.5.2.1"
        ]
    ],
    "ID305": [
        [
            "BA.5.2.35"
        ]
    ],
    "ID306": [
        [
            "BN.1"
        ]
    ],
    "ID307": [
        [
            "BQ.1"
        ]
    ],
    "ID308": [
        [
            "BA.5.2.13"
        ]
    ],
    "ID309": [
        [
            "BQ.1.1"
        ]
    ],
    "ID310": [
        [
            "BA.5.2.13"
        ]
    ],
    "ID311": [
        [
            "other"
        ]
    ],
    "ID312": [
        [
            "BQ.1.1"
        ]
    ],
    "ID313": [
        [
            "BA.5.2.1",
            27524,
            "BA.5.2"
        ]
    ],
    "ID314": [
        [
            "other"
        ]
    ],
    "ID315": [
        [
            "BQ.1.1"
        ]
    ],
    "ID316": [
        [
            "BA.5.2"
        ]
    ],
    "ID317": [
        [
            "BA.5.2.35",
            3787,
            "BN.1"
        ],
        [
            "BN.1",
            22330,
            "other"
        ]
    ],
    "ID318": [
        [
            "BQ.1.1"
        ]
    ],
    "ID319": [
        [
            "BQ.1"
        ]
    ],
    "ID320": [
        [
            "BQ.1"
        ]
    ],
    "ID321": [
        [
            "BQ.1"
        ]
    ],
    "ID322": [
        [
            "BQ.1.8"
        ]
    ],
    "ID323": [
        [
            "other"
        ]
    ],
    "ID324": [
        [
            "BA.5.2"
        ]
    ],
    "ID325": [
        [
            "BQ.1.1.8"
        ]
    ],
    "ID326": [
        [
            "BA.5.2"
        ]
    ],
    "ID327": [
        [
            "BQ.1"
        ]
    ],
    "ID328": [
        [
            "other"
        ]
    ],
    "ID329": [
        [
            "BQ.1.1"
        ]
    ],
    "ID330": [
        [
            "BF.7"
        ]
    ],
    "ID331": [
        [
            "BA.5.2"
        ]
    ],
    "ID332": [
        [
            "BQ.1.1"
        ]
    ],
    "ID333": [
        [
            "BQ.1.8"
        ]
    ],
    "ID334": [
        [
            "BQ.1"
        ]
    ],
    "ID335": [
        [
            "BQ.1"
        ]
    ],
    "ID336": [
        [
            "BQ.1.1"
        ]
    ],
    "ID337": [
        [
            "BQ.1.8"
        ]
    ],
    "ID338": [
        [
            "BQ.1.8"
        ]
    ],
    "ID339": [
        [
            "BN.1"
        ]
    ],
    "ID340": [
        [
            "BQ.1.1"
        ]
    ],
    "ID341": [
        [
            "BQ.1"
        ]
    ],
    "ID342": [
        [
            "BA.5.2"
        ]
    ],
    "ID343": [
        [
            "BA.5.2.1"
        ]
    ],
    "ID344": [
        [
            "BA.5.1"
        ]
    ],
    "ID345": [
        [
            "BA.5.2.13",
            12438,
            "BQ.1.8"
        ]
    ],
    "ID346": [
        [
            "BA.5.1"
        ]
    ],
    "ID347": [
        [
            "BQ.1.1",
            27294,
            "BQ.1"
        ]
    ],
    "ID348": [
        [
            "BA.2.75"
        ]
    ],
    "ID349": [
        [
            "BQ.1"
        ]
    ],
    "ID350": [
        [
            "BA.5.2"
        ]
    ],
    "ID351": [
        [
            "BQ.1.1"
        ]
    ],
    "ID352": [
        [
            "BA.5.2"
        ]
    ],
    "ID353": [
        [
            "BA.5.2",
            27005,
            "BA.5"
        ]
    ],
    "ID354": [
        [
            "BQ.1.1"
        ]
    ],
    "ID355": [
        [
            "BN.1"
        ]
    ],
    "ID356": [
        [
            "BQ.1.1"
        ]
    ],
    "ID357": [
        [
            "BQ.1"
        ]
    ],
    "ID358": [
        [
            "BQ.1.1.8"
        ]
    ],
    "ID359": [
        [
            "BA.4.6"
        ]
    ],
    "ID360": [
        [
            "BF.7"
        ]
    ],
    "ID361": [
        [
            "BF.7"
        ]
    ],
    "ID362": [
        [
            "BQ.1.1"
        ]
    ],
    "ID363": [
        [
            "BQ.1.1"
        ]
    ],
    "ID364": [
        [
            "BQ.1"
        ]
    ],
    "ID365": [
        [
            "BQ.1.1"
        ]
    ],
    "ID366": [
        [
            "BA.5"
        ]
    ],
    "ID367": [
        [
            "BQ.1.1"
        ]
    ],
    "ID368": [
        [
            "BQ.1",
            1859,
            "BA.5"
        ]
    ],
    "ID369": [
        [
            "BQ.1.1"
        ]
    ],
    "ID370": [
        [
            "BQ.1.1"
        ]
    ],
    "ID371": [
        [
            "BN.1"
        ]
    ],
    "ID372": [
        [
            "BF.7"
        ]
    ],
    "ID373": [
        [
            "BA.5.1"
        ]
    ],
    "ID374": [
        [
            "BA.5"
        ]
    ],
    "ID375": [
        [
            "BA.5"
        ]
    ],
    "ID376": [
        [
            "BF.7"
        ]
    ],
    "ID377": [
        [
            "BQ.1"
        ]
    ],
    "ID378": [
        [
            "BQ.1.8"
        ]
    ],
    "ID379": [
        [
            "BQ.1.1"
        ]
    ],
    "ID380": [
        [
            "BQ.1.1"
        ]
    ],
    "ID381": [
        [
            "BA.5.2.1"
        ]
    ],
    "ID382": [
        [
            "BQ.1.1"
        ]
    ],
    "ID383": [
        [
            "BQ.1.1"
        ]
    ],
    "ID384": [
        [
            "BQ.1.8"
        ]
    ],
    "ID385": [
        [
            "BQ.1.1"
        ]
    ],
    "ID386": [
        [
            "BQ.1.1"
        ]
    ],
    "ID387": [
        [
            "BQ.1"
        ]
    ],
    "ID388": [
        [
            "BA.5.2.35"
        ]
    ],
    "ID389": [
        [
            "BA.5.1"
        ]
    ],
    "ID390": [
        [
            "BQ.1.1"
        ]
    ],
    "ID391": [
        [
            "BQ.1.1"
        ]
    ],
    "ID392": [
        [
            "BQ.1.8"
        ]
    ],
    "ID393": [
        [
            "BN.1"
        ]
    ],
    "ID394": [
        [
            "BA.5.1"
        ]
    ],
    "ID395": [
        [
            "BQ.1.1"
        ]
    ],
    "ID396": [
        [
            "BQ.1.1"
        ]
    ],
    "ID397": [
        [
            "BA.2.75"
        ]
    ],
    "ID398": [
        [
            "BN.1"
        ]
    ],
    "ID399": [
        [
            "BQ.1.1.8"
        ]
    ],
    "ID400": [
        [
            "BA.5.2.1"
        ]
    ],
    "ID401": [
        [
            "BQ.1"
        ]
    ],
    "ID402": [
        [
            "BA.5.2.13"
        ]
    ],
    "ID403": [
        [
            "BQ.1.1"
        ]
    ],
    "ID404": [
        [
            "BA.5.2.1",
            3620,
            "BA.5.2"
        ]
    ],
    "ID405": [
        [
            "BA.5.1"
        ]
    ],
    "ID406": [
        [
            "BA.5.2.13"
        ]
    ],
    "ID407": [
        [
            "BA.5.2.1"
        ]
    ],
    "ID408": [
        [
            "BQ.1.1"
        ]
    ],
    "ID409": [
        [
            "BA.5.2.35"
        ]
    ],
    "ID410": [
        [
            "BA.2.75"
        ]
    ],
    "ID411": [
        [
            "BA.5.2"
        ]
    ],
    "ID412": [
        [
            "BF.7"
        ]
    ],
    "ID413": [
        [
            "BA.5.2"
        ]
    ],
    "ID414": [
        [
            "BQ.1.1"
        ]
    ],
    "ID415": [
        [
            "BQ.1"
        ]
    ],
    "ID416": [
        [
            "BA.5.2"
        ]
    ],
    "ID417": [
        [
            "BA.5.2"
        ]
    ],
    "ID418": [
        [
            "BN.1"
        ]
    ],
    "ID419": [
        [
            "BF.7"
        ]
    ],
    "ID420": [
        [
            "BQ.1"
        ]
    ],
    "ID421": [
        [
            "BA.2.75"
        ]
    ],
    "ID422": [
        [
            "other"
        ]
    ],
    "ID423": [
        [
            "BQ.1"
        ]
    ],
    "ID424": [
        [
            "BF.7"
        ]
    ],
    "ID425": [
        [
            "BA.2.75"
        ]
    ],
    "ID426": [
        [
            "BQ.1.1"
        ]
    ],
    "ID427": [
        [
            "BF.7"
        ]
    ],
    "ID428": [
        [
            "BE.1"
        ]
    ],
    "ID429": [
        [
            "BA.5.2"
        ]
    ],
    "ID430": [
        [
            "BQ.1.1.8"
        ]
    ],
    "ID431": [
        [
            "BQ.1.1"
        ]
    ],
    "ID432": [
        [
            "BQ.1.1.8"
        ]
    ],
    "ID433": [
        [
            "BA.5.2",
            2697,
            "BF.7"
        ],
        [
            "BF.7",
            28741,
            "BE.1"
        ]
    ],
    "ID434": [
        [
            "BQ.1.1"
        ]
    ],
    "ID435": [
        [
            "BF.7"
        ]
    ],
    "ID436": [
        [
            "BN.1"
        ]
    ],
    "ID437": [
        [
            "BQ.1.1"
        ]
    ],
    "ID438": [
        [
            "BA.5"
        ]
    ],
    "ID439": [
        [
            "BQ.1"
        ]
    ],
    "ID440": [
        [
            "BA.5.1",
            23170,
            "BA.4.6"
        ]
    ],
    "ID441": [
        [
            "BQ.1.8"
        ]
    ],
    "ID442": [
        [
            "BQ.1.1"
        ]
    ],
    "ID443": [
        [
            "BA.5.2"
        ]
    ],
    "ID444": [
        [
            "BA.5.1"
        ]
    ],
    "ID445": [
        [
            "BQ.1.1"
        ]
    ],
    "ID446": [
        [
            "BQ.1"
        ]
    ],
    "ID447": [
        [
            "BA.5.2"
        ]
    ],
    "ID448": [
        [
            "BQ.1"
        ]
    ],
    "ID449": [
        [
            "BQ.1"
        ]
    ],
    "ID450": [
        [
            "BQ.1.1"
        ]
    ],
    "ID451": [
        [
            "BQ.1.1"
        ]
    ],
    "ID452": [
        [
            "BQ.1.8"
        ]
    ],
    "ID453": [
        [
            "BQ.1"
        ]
    ],
    "ID454": [
        [
            "BF.7"
        ]
    ],
    "ID455": [
        [
            "BF.7"
        ]
    ],
    "ID456": [
        [
            "BA.5.2.1"
        ]
    ],
    "ID457": [
        [
            "BF.7"
        ]
    ],
    "ID458": [
        [
            "BQ.1.1.8"
        ]
    ],
    "ID459": [
        [
            "BF.11"
        ]
    ],
    "ID460": [
        [
            "BQ.1.1"
        ]
    ],
    "ID461": [
        [
            "BQ.1"
        ]
    ],
    "ID462": [
        [
            "BN.1"
        ]
    ],
    "ID463": [
        [
            "BA.2.75"
        ]
    ],
    "ID464": [
        [
            "BQ.1.1"
        ]
    ],
    "ID465": [
        [
            "BQ.1.1"
        ]
    ],
    "ID466": [
        [
            "BQ.1.1"
        ]
    ],
    "ID467": [
        [
            "BQ.1"
        ]
    ],
    "ID468": [
        [
            "BN.1"
        ]
    ],
    "ID469": [
        [
            "BQ.1.8"
        ]
    ],
    "ID470": [
        [
            "BA.2.75"
        ]
    ],
    "ID471": [
        [
            "BQ.1"
        ]
    ],
    "ID472": [
        [
            "BQ.1.1"
        ]
    ],
    "ID473": [
        [
            "BA.5.2"
        ]
    ],
    "ID474": [
        [
            "BA.5.2.1"
        ]
    ],
    "ID475": [
        [
            "other"
        ]
    ],
    "ID476": [
        [
            "BF.7"
        ]
    ],
    "ID477": [
        [
            "BN.1"
        ]
    ],
    "ID478": [
        [
            "BQ.1.1"
        ]
    ],
    "ID479": [
        [
            "BQ.1.8"
        ]
    ],
    "ID480": [
        [
            "BQ.1.1"
        ]
    ],
    "ID481": [
        [
            "BA.2.75",
            28374,
            "BN.1"
        ]
    ],
    "ID482": [
        [
            "BQ.1.8"
        ]
    ],
    "ID483": [
        [
            "BQ.1.1"
        ]
    ],
    "ID484": [
        [
            "BF.7"
        ]
    ],
    "ID485": [
        [
            "BF.7"
        ]
    ],
    "ID486": [
        [
            "BA.5.2.35"
        ]
    ],
    "ID487": [
        [
            "BA.5.2"
        ]
    ],
    "ID488": [
        [
            "BQ.1"
        ]
    ],
    "ID489": [
        [
            "BQ.1"
        ]
    ],
    "ID490": [
        [
            "BQ.1.1"
        ]
    ],
    "ID491": [
        [
            "other"
        ]
    ],
    "ID492": [
        [
            "other"
        ]
    ],
    "ID493": [
        [
            "BQ.1.1"
        ]
    ],
    "ID494": [
        [
            "BA.5.2.35"
        ]
    ],
    "ID495": [
        [
            "BA.5.2"
        ]
    ],
    "ID496": [
        [
            "BA.5.2.1"
        ]
    ],
    "ID497": [
        [
            "other"
        ]
    ],
    "ID498": [
        [
            "BA.5.1"
        ]
    ],
    "ID499": [
        [
            "BA.5.1"
        ]
    ],
    "ID500": [
        [
            "BA.5.2.35"
        ]
    ],
    "ID501": [
        [
            "BQ.1.1"
        ]
    ],
    "ID502": [
        [
            "BQ.1.1"
        ]
    ],
    "ID503": [
        [
            "BA.5.2"
        ]
    ],
    "ID504": [
        [
            "BA.5.2"
        ]
    ],
    "ID505": [
        [
            "BQ.1"
        ]
    ],
    "ID506": [
        [
            "BA.2.75"
        ]
    ],
    "ID507": [
        [
            "BA.5.2"
        ]
    ],
    "ID508": [
        [
            "BQ.1.1"
        ]
    ],
    "ID509": [
        [
            "BN.1"
        ]
    ],
    "ID510": [
        [
            "BQ.1.1"
        ]
    ],
    "ID511": [
        [
            "BQ.1.1"
        ]
    ],
    "ID512": [
        [
            "BA.5.2.1"
        ]
    ],
    "ID513": [
        [
            "BQ.1.8",
            23624,
            "BQ.1.1"
        ]
    ],
    "ID514": [
        [
            "BQ.1"
        ]
    ],
    "ID515": [
        [
            "BQ.1.1.8"
        ]
    ],
    "ID516": [
        [
            "BQ.1.1"
        ]
    ],
    "ID517": [
        [
            "BF.7"
        ]
    ],
    "ID518": [
        [
            "BE.1",
            188,
            "BQ.1.1"
        ]
    ],
    "ID519": [
        [
            "BQ.1.1"
        ]
    ],
    "ID520": [
        [
            "other"
        ]
    ],
    "ID521": [
        [
            "BQ.1"
        ]
    ],
    "ID522": [
        [
            "BF.7"
        ]
    ],
    "ID523": [
        [
            "BF.11"
        ]
    ],
    "ID524": [
        [
            "BQ.1.1"
        ]
    ],
    "ID525": [
        [
            "BQ.1.8"
        ]
    ],
    "ID526": [
        [
            "BQ.1.1"
        ]
    ],
    "ID527": [
        [
            "BA.5.1"
        ]
    ],
    "ID528": [
        [
            "BN.1"
        ]
    ],
    "ID529": [
        [
            "BA.5.2.35"
        ]
    ],
    "ID530": [
        [
            "BQ.1"
        ]
    ],
    "ID531": [
        [
            "BA.5.2.13"
        ]
    ],
    "ID532": [
        [
            "BA.5.2"
        ]
    ],
    "ID533": [
        [
            "BN.1"
        ]
    ],
    "ID534": [
        [
            "BA.5.2.13"
        ]
    ],
    "ID535": [
        [
            "BF.7"
        ]
    ],
    "ID536": [
        [
            "BF.7"
        ]
    ],
    "ID537": [
        [
            "BQ.1"
        ]
    ],
    "ID538": [
        [
            "BQ.1.1"
        ]
    ],
    "ID539": [
        [
            "BQ.1.1"
        ]
    ],
    "ID540": [
        [
            "BA.5.1"
        ]
    ],
    "ID541": [
        [
            "BQ.1.1"
        ]
    ],
    "ID542": [
        [
            "BA.5.1",
            23170,
            "BA.4.6"
        ]
    ],
    "ID543": [
        [
            "BA.5.2"
        ]
    ],
    "ID544": [
        [
            "BQ.1"
        ]
    ],
    "ID545": [
        [
            "BQ.1.1"
        ]
    ],
    "ID546": [
        [
            "BA.5.2"
        ]
    ],
    "ID547": [
        [
            "BQ.1.1"
        ]
    ],
    "ID548": [
        [
            "BA.5.2"
        ]
    ],
    "ID549": [
        [
            "BQ.1"
        ]
    ],
    "ID550": [
        [
            "BQ.1.1"
        ]
    ],
    "ID551": [
        [
            "BA.5.2"
        ]
    ],
    "ID552": [
        [
            "other"
        ]
    ],
    "ID553": [
        [
            "other"
        ]
    ],
    "ID554": [
        [
            "BA.5.1"
        ]
    ],
    "ID555": [
        [
            "BA.2.75"
        ]
    ],
    "ID556": [
        [
            "BQ.1.1"
        ]
    ],
    "ID557": [
        [
            "BA.5",
            883,
            "BA.5.2"
        ]
    ],
    "ID558": [
        [
            "BQ.1.1"
        ]
    ],
    "ID559": [
        [
            "BF.7"
        ]
    ],
    "ID560": [
        [
            "BQ.1"
        ]
    ],
    "ID561": [
        [
            "BF.7"
        ]
    ],
    "ID562": [
        [
            "BQ.1.1"
        ]
    ],
    "ID563": [
        [
            "BQ.1"
        ]
    ],
    "ID564": [
        [
            "BF.11"
        ]
    ],
    "ID565": [
        [
            "other"
        ]
    ],
    "ID566": [
        [
            "BQ.1"
        ]
    ],
    "ID567": [
        [
            "BA.5.1"
        ]
    ],
    "ID568": [
        [
            "BQ.1.1"
        ]
    ],
    "ID569": [
        [
            "BN.1"
        ]
    ],
    "ID570": [
        [
            "BA.5.2"
        ]
    ],
    "ID571": [
        [
            "BF.7"
        ]
    ],
    "ID572": [
        [
            "BA.5.2.1"
        ]
    ],
    "ID573": [
        [
            "BQ.1.1.8"
        ]
    ],
    "ID574": [
        [
            "BN.1"
        ]
    ],
    "ID575": [
        [
            "BA.2.75"
        ]
    ],
    "ID576": [
        [
            "BA.5.1"
        ]
    ],
    "ID577": [
        [
            "BA.5.2.35"
        ]
    ],
    "ID578": [
        [
            "BQ.1.1"
        ]
    ],
    "ID579": [
        [
            "BQ.1.1"
        ]
    ],
    "ID580": [
        [
            "BQ.1.1"
        ]
    ],
    "ID581": [
        [
            "BN.1"
        ]
    ],
    "ID582": [
        [
            "BQ.1.8"
        ]
    ],
    "ID583": [
        [
            "BQ.1.1.8"
        ]
    ],
    "ID584": [
        [
            "BQ.1.1"
        ]
    ],
    "ID585": [
        [
            "BA.5.2"
        ]
    ],
    "ID586": [
        [
            "BQ.1.1"
        ]
    ],
    "ID587": [
        [
            "BQ.1"
        ]
    ],
    "ID588": [
        [
            "BQ.1.1"
        ]
    ],
    "ID589": [
        [
            "BA.5.2"
        ]
    ],
    "ID590": [
        [
            "BA.5.1"
        ]
    ],
    "ID591": [
        [
            "BQ.1.8"
        ]
    ],
    "ID592": [
        [
            "BQ.1.1"
        ]
    ],
    "ID593": [
        [
            "BA.5.2"
        ]
    ],
    "ID594": [
        [
            "BQ.1.1"
        ]
    ],
    "ID595": [
        [
            "BF.7"
        ]
    ],
    "ID596": [
        [
            "BA.5.2.1"
        ]
    ],
    "ID597": [
        [
            "BA.2.75"
        ]
    ],
    "ID598": [
        [
            "BN.1"
        ]
    ],
    "ID599": [
        [
            "BA.5.2"
        ]
    ],
    "ID600": [
        [
            "BA.5.2"
        ]
    ],
    "ID601": [
        [
            "BQ.1.1"
        ]
    ],
    "ID602": [
        [
            "BQ.1.1.8",
            1362,
            "BA.5.2"
        ]
    ],
    "ID603": [
        [
            "BA.5.2"
        ]
    ],
    "ID604": [
        [
            "BQ.1.1"
        ]
    ],
    "ID605": [
        [
            "other"
        ]
    ],
    "ID606": [
        [
            "other"
        ]
    ],
    "ID607": [
        [
            "BQ.1.1"
        ]
    ],
    "ID608": [
        [
            "BQ.1.8"
        ]
    ],
    "ID609": [
        [
            "BF.7"
        ]
    ],
    "ID610": [
        [
            "BA.2.75"
        ]
    ],
    "ID611": [
        [
            "BQ.1"
        ]
    ],
    "ID612": [
        [
            "BQ.1.1.8"
        ]
    ],
    "ID613": [
        [
            "BA.5.2"
        ]
    ],
    "ID614": [
        [
            "BQ.1"
        ]
    ],
    "ID615": [
        [
            "BA.5.2"
        ]
    ],
    "ID616": [
        [
            "BQ.1"
        ]
    ],
    "ID617": [
        [
            "BA.5.2"
        ]
    ],
    "ID618": [
        [
            "other"
        ]
    ],
    "ID619": [
        [
            "BA.5.2.35"
        ]
    ],
    "ID620": [
        [
            "BQ.1.1"
        ]
    ],
    "ID621": [
        [
            "BF.7"
        ]
    ],
    "ID622": [
        [
            "other"
        ]
    ],
    "ID623": [
        [
            "other"
        ]
    ],
    "ID624": [
        [
            "BQ.1.8"
        ]
    ],
    "ID625": [
        [
            "BQ.1.1"
        ]
    ],
    "ID626": [
        [
            "BQ.1"
        ]
    ],
    "ID627": [
        [
            "BQ.1.1"
        ]
    ],
    "ID628": [
        [
            "BQ.1.1"
        ]
    ],
    "ID629": [
        [
            "BN.1"
        ]
    ],
    "ID630": [
        [
            "BF.7"
        ]
    ],
    "ID631": [
        [
            "BQ.1"
        ]
    ],
    "ID632": [
        [
            "BQ.1.1"
        ]
    ],
    "ID633": [
        [
            "BQ.1"
        ]
    ],
    "ID634": [
        [
            "other"
        ]
    ],
    "ID635": [
        [
            "BQ.1.1"
        ]
    ],
    "ID636": [
        [
            "BQ.1.1"
        ]
    ],
    "ID637": [
        [
            "BF.11"
        ]
    ],
    "ID638": [
        [
            "BQ.1.1"
        ]
    ],
    "ID639": [
        [
            "BQ.1.1"
        ]
    ],
    "ID640": [
        [
            "BQ.1.1"
        ]
    ],
    "ID641": [
        [
            "BQ.1.1",
            23634,
            "BQ.1.8"
        ],
        [
            "BQ.1.8",
            27742,
            "BE.1"
        ]
    ],
    "ID642": [
        [
            "BA.5.2"
        ]
    ],
    "ID643": [
        [
            "BF.11"
        ]
    ],
    "ID644": [
        [
            "BA.5.2.1"
        ]
    ],
    "ID645": [
        [
            "BQ.1",
            28727,
            "other"
        ]
    ],
    "ID646": [
        [
            "BN.1"
        ]
    ],
    "ID647": [
        [
            "BQ.1.1"
        ]
    ],
    "ID648": [
        [
            "BQ.1.1"
        ]
    ],
    "ID649": [
        [
            "BA.5.2"
        ]
    ],
    "ID650": [
        [
            "BQ.1.8",
            25852,
            "BQ.1"
        ]
    ],
    "ID651": [
        [
            "BQ.1.1"
        ]
    ],
    "ID652": [
        [
            "other"
        ]
    ],
    "ID653": [
        [
            "BF.7"
        ]
    ],
    "ID654": [
        [
            "BN.1"
        ]
    ],
    "ID655": [
        [
            "other"
        ]
    ],
    "ID656": [
        [
            "BQ.1.1"
        ]
    ],
    "ID657": [
        [
            "BQ.1.1"
        ]
    ],
    "ID658": [
        [
            "BQ.1.1"
        ]
    ],
    "ID659": [
        [
            "BN.1"
        ]
    ],
    "ID660": [
        [
            "BQ.1.1"
        ]
    ],
    "ID661": [
        [
            "BQ.1.8"
        ]
    ],
    "ID662": [
        [
            "BQ.1.1"
        ]
    ],
    "ID663": [
        [
            "BA.5.2.1"
        ]
    ],
    "ID664": [
        [
            "BQ.1.1"
        ]
    ],
    "ID665": [
        [
            "BQ.1.1"
        ]
    ],
    "ID666": [
        [
            "BQ.1.1"
        ]
    ],
    "ID667": [
        [
            "BA.5.2.35"
        ]
    ],
    "ID668": [
        [
            "BF.7"
        ]
    ],
    "ID669": [
        [
            "BQ.1.1"
        ]
    ],
    "ID670": [
        [
            "BQ.1.1"
        ]
    ],
    "ID671": [
        [
            "BF.11"
        ]
    ],
    "ID672": [
        [
            "BA.5"
        ]
    ],
    "ID673": [
        [
            "BQ.1.1"
        ]
    ],
    "ID674": [
        [
            "BQ.1.1"
        ]
    ],
    "ID675": [
        [
            "BF.7"
        ]
    ],
    "ID676": [
        [
            "BA.5.2.1"
        ]
    ],
    "ID677": [
        [
            "BQ.1"
        ]
    ],
    "ID678": [
        [
            "BA.2.75"
        ]
    ],
    "ID679": [
        [
            "other"
        ]
    ],
    "ID680": [
        [
            "BA.5.2.13"
        ]
    ],
    "ID681": [
        [
            "BF.7"
        ]
    ],
    "ID682": [
        [
            "BQ.1.8"
        ]
    ],
    "ID683": [
        [
            "BQ.1"
        ]
    ],
    "ID684": [
        [
            "BN.1"
        ]
    ],
    "ID685": [
        [
            "BA.5.2"
        ]
    ],
    "ID686": [
        [
            "BQ.1.8"
        ]
    ],
    "ID687": [
        [
            "other",
            26180,
            "BA.5.2.13"
        ]
    ],
    "ID688": [
        [
            "BQ.1.1.8"
        ]
    ],
    "ID689": [
        [
            "BQ.1.1"
        ]
    ],
    "ID690": [
        [
            "BF.7",
            29631,
            "BA.5.2.1"
        ]
    ],
    "ID691": [
        [
            "BQ.1.1"
        ]
    ],
    "ID692": [
        [
            "BA.5.2"
        ]
    ],
    "ID693": [
        [
            "BA.5.1"
        ]
    ],
    "ID694": [
        [
            "BN.1"
        ]
    ],
    "ID695": [
        [
            "BQ.1.1"
        ]
    ],
    "ID696": [
        [
            "BQ.1.1"
        ]
    ],
    "ID697": [
        [
            "BQ.1.1"
        ]
    ],
    "ID698": [
        [
            "BQ.1"
        ]
    ],
    "ID699": [
        [
            "BQ.1"
        ]
    ],
    "ID700": [
        [
            "BA.5.2.1"
        ]
    ],
    "ID701": [
        [
            "BA.2.75"
        ]
    ],
    "ID702": [
        [
            "BQ.1"
        ]
    ],
    "ID703": [
        [
            "BQ.1.1"
        ]
    ],
    "ID704": [
        [
            "BA.5.2.1"
        ]
    ],
    "ID705": [
        [
            "BA.5.2",
            12049,
            "BA.5"
        ]
    ],
    "ID706": [
        [
            "BQ.1.1"
        ]
    ],
    "ID707": [
        [
            "BA.5.1"
        ]
    ],
    "ID708": [
        [
            "BA.5.2.1"
        ]
    ],
    "ID709": [
        [
            "BA.5.2.1"
        ]
    ],
    "ID710": [
        [
            "BA.5.1"
        ]
    ],
    "ID711": [
        [
            "BQ.1.1"
        ]
    ],
    "ID712": [
        [
            "BF.7"
        ]
    ],
    "ID713": [
        [
            "BN.1"
        ]
    ],
    "ID714": [
        [
            "BA.5.2.1"
        ]
    ],
    "ID715": [
        [
            "BA.5.2"
        ]
    ],
    "ID716": [
        [
            "BA.5.2.13"
        ]
    ],
    "ID717": [
        [
            "BA.5.2"
        ]
    ],
    "ID718": [
        [
            "BQ.1.1"
        ]
    ],
    "ID719": [
        [
            "BE.1",
            16934,
            "BA.5.2.1"
        ]
    ],
    "ID720": [
        [
            "BQ.1.1"
        ]
    ],
    "ID721": [
        [
            "BF.7"
        ]
    ],
    "ID722": [
        [
            "BA.4.6"
        ]
    ],
    "ID723": [
        [
            "BQ.1.1"
        ]
    ],
    "ID724": [
        [
            "BF.7"
        ]
    ],
    "ID725": [
        [
            "BQ.1"
        ]
    ],
    "ID726": [
        [
            "BQ.1.1"
        ]
    ],
    "ID727": [
        [
            "BQ.1.1.8"
        ]
    ],
    "ID728": [
        [
            "BF.11"
        ]
    ],
    "ID729": [
        [
            "BA.5.2"
        ]
    ],
    "ID730": [
        [
            "BA.5.1"
        ]
    ],
    "ID731": [
        [
            "BQ.1.1"
        ]
    ],
    "ID732": [
        [
            "BA.2.75"
        ]
    ],
    "ID733": [
        [
            "BN.1"
        ]
    ],
    "ID734": [
        [
            "BA.5.2.35"
        ]
    ],
    "ID735": [
        [
            "BQ.1"
        ]
    ],
    "ID736": [
        [
            "BQ.1.1"
        ]
    ],
    "ID737": [
        [
            "BQ.1.1"
        ]
    ],
    "ID738": [
        [
            "BN.1"
        ]
    ],
    "ID739": [
        [
            "BN.1"
        ]
    ],
    "ID740": [
        [
            "BN.1"
        ]
    ],
    "ID741": [
        [
            "BQ.1.1"
        ]
    ],
    "ID742": [
        [
            "BA.5.2"
        ]
    ],
    "ID743": [
        [
            "BA.5.2"
        ]
    ],
    "ID744": [
        [
            "BF.7"
        ]
    ],
    "ID745": [
        [
            "BQ.1.1"
        ]
    ],
    "ID746": [
        [
            "BQ.1.1"
        ]
    ],
    "ID747": [
        [
            "BQ.1.1"
        ]
    ],
    "ID748": [
        [
            "BQ.1.1"
        ]
    ],
    "ID749": [
        [
            "BQ.1"
        ]
    ],
    "ID750": [
        [
            "BA.5.2"
        ]
    ],
    "ID751": [
        [
            "other"
        ]
    ],
    "ID752": [
        [
            "BQ.1.1"
        ]
    ],
    "ID753": [
        [
            "BQ.1.1"
        ]
    ],
    "ID754": [
        [
            "BQ.1.1"
        ]
    ],
    "ID755": [
        [
            "other"
        ]
    ],
    "ID756": [
        [
            "BF.7"
        ]
    ],
    "ID757": [
        [
            "BA.4.6"
        ]
    ],
    "ID758": [
        [
            "BQ.1.1"
        ]
    ],
    "ID759": [
        [
            "BQ.1.1"
        ]
    ],
    "ID760": [
        [
            "other"
        ]
    ],
    "ID761": [
        [
            "BA.2.75"
        ]
    ],
    "ID762": [
        [
            "BQ.1.1"
        ]
    ],
    "ID763": [
        [
            "BA.5.1"
        ]
    ],
    "ID764": [
        [
            "BF.11"
        ]
    ],
    "ID765": [
        [
            "BQ.1"
        ]
    ],
    "ID766": [
        [
            "BQ.1.1.8"
        ]
    ],
    "ID767": [
        [
            "BQ.1"
        ]
    ],
    "ID768": [
        [
            "BF.7"
        ]
    ],
    "ID769": [
        [
            "BA.5.2"
        ]
    ],
    "ID770": [
        [
            "BQ.1.1.8"
        ]
    ],
    "ID771": [
        [
            "BQ.1.8"
        ]
    ],
    "ID772": [
        [
            "BQ.1.1"
        ]
    ],
    "ID773": [
        [
            "BA.5.2"
        ]
    ],
    "ID774": [
        [
            "BF.7"
        ]
    ],
    "ID775": [
        [
            "BN.1"
        ]
    ],
    "ID776": [
        [
            "BQ.1.1"
        ]
    ],
    "ID777": [
        [
            "BQ.1.8"
        ]
    ],
    "ID778": [
        [
            "BA.5.2",
            11545,
            "BA.5.2.1"
        ]
    ],
    "ID779": [
        [
            "BQ.1"
        ]
    ],
    "ID780": [
        [
            "BF.7"
        ]
    ],
    "ID781": [
        [
            "BQ.1.1"
        ]
    ],
    "ID782": [
        [
            "BQ.1"
        ]
    ],
    "ID783": [
        [
            "BQ.1.1"
        ]
    ],
    "ID784": [
        [
            "BA.2.75"
        ]
    ],
    "ID785": [
        [
            "BQ.1.1"
        ]
    ],
    "ID786": [
        [
            "BQ.1.1.8"
        ]
    ],
    "ID787": [
        [
            "BA.2.75"
        ]
    ],
    "ID788": [
        [
            "BA.5.1"
        ]
    ],
    "ID789": [
        [
            "BA.5.2"
        ]
    ],
    "ID790": [
        [
            "BQ.1.1"
        ]
    ],
    "ID791": [
        [
            "BN.1"
        ]
    ],
    "ID792": [
        [
            "BF.7"
        ]
    ],
    "ID793": [
        [
            "other",
            139,
            "BF.11"
        ]
    ],
    "ID794": [
        [
            "BA.5.2"
        ]
    ],
    "ID795": [
        [
            "BQ.1.1"
        ]
    ],
    "ID796": [
        [
            "BA.5.1"
        ]
    ],
    "ID797": [
        [
            "BQ.1.1"
        ]
    ],
    "ID798": [
        [
            "BQ.1.1"
        ]
    ],
    "ID799": [
        [
            "BQ.1.1",
            29773,
            "other"
        ]
    ],
    "ID800": [
        [
            "other"
        ]
    ],
    "ID801": [
        [
            "BQ.1"
        ]
    ],
    "ID802": [
        [
            "BQ.1.1"
        ]
    ],
    "ID803": [
        [
            "BA.5.1"
        ]
    ],
    "ID804": [
        [
            "BQ.1.1"
        ]
    ],
    "ID805": [
        [
            "BQ.1.1"
        ]
    ],
    "ID806": [
        [
            "BQ.1.1.8"
        ]
    ],
    "ID807": [
        [
            "BA.5.1"
        ]
    ],
    "ID808": [
        [
            "BA.5.2"
        ]
    ],
    "ID809": [
        [
            "BQ.1.1"
        ]
    ],
    "ID810": [
        [
            "BQ.1.1"
        ]
    ],
    "ID811": [
        [
            "BA.5.2"
        ]
    ],
    "ID812": [
        [
            "BA.5.1"
        ]
    ],
    "ID813": [
        [
            "BN.1"
        ]
    ],
    "ID814": [
        [
            "BN.1"
        ]
    ],
    "ID815": [
        [
            "BQ.1"
        ]
    ],
    "ID816": [
        [
            "BQ.1.1"
        ]
    ],
    "ID817": [
        [
            "BA.5.2.35"
        ]
    ],
    "ID818": [
        [
            "other"
        ]
    ],
    "ID819": [
        [
            "BQ.1.1"
        ]
    ],
    "ID820": [
        [
            "BQ.1.1"
        ]
    ],
    "ID821": [
        [
            "BA.5.2.1"
        ]
    ],
    "ID822": [
        [
            "BQ.1.1"
        ]
    ],
    "ID823": [
        [
            "BQ.1.1"
        ]
    ],
    "ID824": [
        [
            "BA.5.2"
        ]
    ],
    "ID825": [
        [
            "BA.5.1"
        ]
    ],
    "ID826": [
        [
            "BQ.1.8"
        ]
    ],
    "ID827": [
        [
            "BA.5.1"
        ]
    ],
    "ID828": [
        [
            "other"
        ]
    ],
    "ID829": [
        [
            "BA.4.6"
        ]
    ],
    "ID830": [
        [
            "BN.1"
        ]
    ],
    "ID831": [
        [
            "BQ.1.1"
        ]
    ],
    "ID832": [
        [
            "BN.1"
        ]
    ],
    "ID833": [
        [
            "BQ.1.1"
        ]
    ],
    "ID834": [
        [
            "BA.5.2.13"
        ]
    ],
    "ID835": [
        [
            "BQ.1.1"
        ]
    ],
    "ID836": [
        [
            "BQ.1.1"
        ]
    ],
    "ID837": [
        [
            "BQ.1"
        ]
    ],
    "ID838": [
        [
            "BF.7"
        ]
    ],
    "ID839": [
        [
            "BQ.1.1"
        ]
    ],
    "ID840": [
        [
            "BQ.1.1"
        ]
    ],
    "ID841": [
        [
            "BF.7"
        ]
    ],
    "ID842": [
        [
            "BQ.1.1"
        ]
    ],
    "ID843": [
        [
            "BQ.1.1"
        ]
    ],
    "ID844": [
        [
            "BA.5",
            10115,
            "other"
        ],
        [
            "other",
            11530,
            "BA.5.1"
        ],
        [
            "BA.5.1",
            22346,
            "BA.5"
        ]
    ],
    "ID845": [
        [
            "BQ.1.1"
        ]
    ],
    "ID846": [
        [
            "BQ.1.1"
        ]
    ],
    "ID847": [
        [
            "BA.5.2.13"
        ]
    ],
    "ID848": [
        [
            "BQ.1.1"
        ]
    ],
    "ID849": [
        [
            "BQ.1.1"
        ]
    ],
    "ID850": [
        [
            "BQ.1.1.8"
        ]
    ],
    "ID851": [
        [
            "BA.5.2"
        ]
    ],
    "ID852": [
        [
            "BA.2.75"
        ]
    ],
    "ID853": [
        [
            "BA.2.75"
        ]
    ],
    "ID854": [
        [
            "BA.5.2.13"
        ]
    ],
    "ID855": [
        [
            "BQ.1"
        ]
    ],
    "ID856": [
        [
            "BQ.1.1"
        ]
    ],
    "ID857": [
        [
            "BQ.1.1"
        ]
    ],
    "ID858": [
        [
            "BA.5.2"
        ]
    ],
    "ID859": [
        [
            "BQ.1.1"
        ]
    ],
    "ID860": [
        [
            "BQ.1.1"
        ]
    ],
    "ID861": [
        [
            "BQ.1.1"
        ]
    ],
    "ID862": [
        [
            "BN.1"
        ]
    ],
    "ID863": [
        [
            "BQ.1"
        ]
    ],
    "ID864": [
        [
            "BA.5.2"
        ]
    ],
    "ID865": [
        [
            "BF.7"
        ]
    ],
    "ID866": [
        [
            "BA.5.2"
        ]
    ],
    "ID867": [
        [
            "BA.5.2"
        ]
    ],
    "ID868": [
        [
            "BA.5.2.35"
        ]
    ],
    "ID869": [
        [
            "BA.2.75"
        ]
    ],
    "ID870": [
        [
            "BF.11"
        ]
    ],
    "ID871": [
        [
            "BA.5.2"
        ]
    ],
    "ID872": [
        [
            "BQ.1.1"
        ]
    ],
    "ID873": [
        [
            "BQ.1.8"
        ]
    ],
    "ID874": [
        [
            "BA.2.75"
        ]
    ],
    "ID875": [
        [
            "BQ.1.1"
        ]
    ],
    "ID876": [
        [
            "BA.5.2"
        ]
    ],
    "ID877": [
        [
            "BQ.1.8"
        ]
    ],
    "ID878": [
        [
            "BQ.1.1"
        ]
    ],
    "ID879": [
        [
            "BQ.1.1"
        ]
    ],
    "ID880": [
        [
            "BQ.1.1"
        ]
    ],
    "ID881": [
        [
            "BA.5.2.1"
        ]
    ],
    "ID882": [
        [
            "BQ.1.1"
        ]
    ],
    "ID883": [
        [
            "BQ.1"
        ]
    ],
    "ID884": [
        [
            "BQ.1"
        ]
    ],
    "ID885": [
        [
            "BQ.1.1"
        ]
    ],
    "ID886": [
        [
            "BQ.1"
        ]
    ],
    "ID887": [
        [
            "BQ.1.1.8"
        ]
    ],
    "ID888": [
        [
            "BQ.1.1"
        ]
    ],
    "ID889": [
        [
            "BQ.1.8"
        ]
    ],
    "ID890": [
        [
            "BA.2.75"
        ]
    ],
    "ID891": [
        [
            "BQ.1.1"
        ]
    ],
    "ID892": [
        [
            "BA.2.75"
        ]
    ],
    "ID893": [
        [
            "BQ.1.1"
        ]
    ],
    "ID894": [
        [
            "BQ.1.1"
        ]
    ],
    "ID895": [
        [
            "BQ.1.8"
        ]
    ],
    "ID896": [
        [
            "BQ.1"
        ]
    ],
    "ID897": [
        [
            "BA.2.75"
        ]
    ],
    "ID898": [
        [
            "BA.2.75"
        ]
    ],
    "ID899": [
        [
            "BQ.1.1"
        ]
    ],
    "ID900": [
        [
            "BA.2.75"
        ]
    ],
    "ID901": [
        [
            "BQ.1.1"
        ]
    ],
    "ID902": [
        [
            "BA.5.1"
        ]
    ],
    "ID903": [
        [
            "BF.7"
        ]
    ],
    "ID904": [
        [
            "BQ.1"
        ]
    ],
    "ID905": [
        [
            "BQ.1.1"
        ]
    ],
    "ID906": [
        [
            "BQ.1",
            28720,
            "BA.5.2.13"
        ]
    ],
    "ID907": [
        [
            "BA.5.2.35"
        ]
    ],
    "ID908": [
        [
            "BN.1"
        ]
    ],
    "ID909": [
        [
            "BA.5.2"
        ]
    ],
    "ID910": [
        [
            "BQ.1.1"
        ]
    ],
    "ID911": [
        [
            "BQ.1.1"
        ]
    ],
    "ID912": [
        [
            "other"
        ]
    ],
    "ID913": [
        [
            "BQ.1.1"
        ]
    ],
    "ID914": [
        [
            "BQ.1.1"
        ]
    ],
    "ID915": [
        [
            "BQ.1.1"
        ]
    ],
    "ID916": [
        [
            "BQ.1.1"
        ]
    ],
    "ID917": [
        [
            "BQ.1.1"
        ]
    ],
    "ID918": [
        [
            "BA.5.2"
        ]
    ],
    "ID919": [
        [
            "BQ.1"
        ]
    ],
    "ID920": [
        [
            "BQ.1.1"
        ]
    ],
    "ID921": [
        [
            "BF.7"
        ]
    ],
    "ID922": [
        [
            "BN.1"
        ]
    ],
    "ID923": [
        [
            "BQ.1.8"
        ]
    ],
    "ID924": [
        [
            "BQ.1.1"
        ]
    ],
    "ID925": [
        [
            "BA.5.2.35"
        ]
    ],
    "ID926": [
        [
            "BQ.1"
        ]
    ],
    "ID927": [
        [
            "BA.5.2.1"
        ]
    ],
    "ID928": [
        [
            "BA.2.75"
        ]
    ],
    "ID929": [
        [
            "BN.1"
        ]
    ],
    "ID930": [
        [
            "BF.7"
        ]
    ],
    "ID931": [
        [
            "BN.1"
        ]
    ],
    "ID932": [
        [
            "BQ.1"
        ]
    ],
    "ID933": [
        [
            "BQ.1.1"
        ]
    ],
    "ID934": [
        [
            "BQ.1.1"
        ]
    ],
    "ID935": [
        [
            "BN.1"
        ]
    ],
    "ID936": [
        [
            "BQ.1"
        ]
    ],
    "ID937": [
        [
            "BQ.1"
        ]
    ],
    "ID938": [
        [
            "BQ.1.1"
        ]
    ],
    "ID939": [
        [
            "BQ.1.1"
        ]
    ],
    "ID940": [
        [
            "BA.2.75",
            26551,
            "BN.1"
        ]
    ],
    "ID941": [
        [
            "BA.5.2.35"
        ]
    ],
    "ID942": [
        [
            "BQ.1.1.8"
        ]
    ],
    "ID943": [
        [
            "BQ.1"
        ]
    ],
    "ID944": [
        [
            "BQ.1.8"
        ]
    ],
    "ID945": [
        [
            "BQ.1.8"
        ]
    ],
    "ID946": [
        [
            "BQ.1.1"
        ]
    ],
    "ID947": [
        [
            "BQ.1.8"
        ]
    ],
    "ID948": [
        [
            "other"
        ]
    ],
    "ID949": [
        [
            "BQ.1"
        ]
    ],
    "ID950": [
        [
            "BQ.1.1"
        ]
    ],
    "ID951": [
        [
            "BQ.1.8"
        ]
    ],
    "ID952": [
        [
            "BQ.1.1",
            29773,
            "other"
        ]
    ],
    "ID953": [
        [
            "BF.7"
        ]
    ],
    "ID954": [
        [
            "BF.7"
        ]
    ],
    "ID955": [
        [
            "BA.5"
        ]
    ],
    "ID956": [
        [
            "BQ.1.1"
        ]
    ],
    "ID957": [
        [
            "BQ.1.1"
        ]
    ],
    "ID958": [
        [
            "BQ.1.8"
        ]
    ],
    "ID959": [
        [
            "BQ.1.1"
        ]
    ],
    "ID960": [
        [
            "BA.5"
        ]
    ],
    "ID961": [
        [
            "BQ.1.1"
        ]
    ],
    "ID962": [
        [
            "BQ.1.1"
        ]
    ],
    "ID963": [
        [
            "BQ.1"
        ]
    ],
    "ID964": [
        [
            "BQ.1"
        ]
    ],
    "ID965": [
        [
            "BQ.1.1.8"
        ]
    ],
    "ID966": [
        [
            "BQ.1.1"
        ]
    ],
    "ID967": [
        [
            "BA.2.75"
        ]
    ],
    "ID968": [
        [
            "BQ.1.1"
        ]
    ],
    "ID969": [
        [
            "BA.5.2.1"
        ]
    ],
    "ID970": [
        [
            "BA.5.1"
        ]
    ],
    "ID971": [
        [
            "BA.5.2"
        ]
    ],
    "ID972": [
        [
            "BQ.1.1.8"
        ]
    ],
    "ID973": [
        [
            "BA.5.1"
        ]
    ],
    "ID974": [
        [
            "other"
        ]
    ],
    "ID975": [
        [
            "BQ.1.1"
        ]
    ],
    "ID976": [
        [
            "BQ.1.1"
        ]
    ],
    "ID977": [
        [
            "BA.5.2"
        ]
    ],
    "ID978": [
        [
            "BF.7"
        ]
    ],
    "ID979": [
        [
            "BN.1"
        ]
    ],
    "ID980": [
        [
            "BQ.1.1"
        ]
    ],
    "ID981": [
        [
            "BQ.1.1"
        ]
    ],
    "ID982": [
        [
            "BQ.1.1"
        ]
    ],
    "ID983": [
        [
            "BQ.1"
        ]
    ],
    "ID984": [
        [
            "BQ.1"
        ]
    ],
    "ID985": [
        [
            "BQ.1",
            22599,
            "BQ.1.1"
        ]
    ],
    "ID986": [
        [
            "BF.7"
        ]
    ],
    "ID987": [
        [
            "BQ.1"
        ]
    ],
    "ID988": [
        [
            "BA.2.75"
        ]
    ],
    "ID989": [
        [
            "BA.5.2.35",
            2324,
            "BQ.1.1"
        ]
    ],
    "ID990": [
        [
            "BQ.1.1"
        ]
    ],
    "ID991": [
        [
            "BF.7"
        ]
    ],
    "ID992": [
        [
            "other"
        ]
    ],
    "ID993": [
        [
            "BQ.1.8"
        ]
    ],
    "ID994": [
        [
            "BQ.1.1"
        ]
    ],
    "ID995": [
        [
            "BQ.1"
        ]
    ],
    "ID996": [
        [
            "BQ.1.1"
        ]
    ],
    "ID997": [
        [
            "BF.7"
        ]
    ],
    "ID998": [
        [
            "BQ.1.1"
        ]
    ],
    "ID999": [
        [
            "BQ.1"
        ]
    ],
    "ID1000": [
        [
            "BQ.1.1"
        ]
    ]
}